{
  "$schema": "https://json-schema.org/draft/2020-12/schema",
  "$id": "https://whats-service/schemas/event.tts.done.schema.json",
  "title": "EventTtsDone",
  "description": "Server event: TTS audio playback completed.",
  "type": "object",
  "required": ["type", "sessionId", "actionId", "timestamp", "payload"],
  "properties": {
    "type": { "const": "tts.done" },
    "sessionId": { "type": "string", "format": "uuid" },
    "actionId": { "type": "string", "format": "uuid" },
    "timestamp": { "type": "integer" },
    "payload": {
      "type": "object",
      "required": ["durationMs"],
      "properties": {
        "durationMs": {
          "type": "integer",
          "description": "Total TTS playback duration in milliseconds."
        }
      },
      "additionalProperties": false
    }
  },
  "additionalProperties": false
}
